synfras/__init__.py
synfras/config.py
synfras/database.py
synfras/parallel.py
synfras/utils.py
synfras-1.0.1.dist-info/METADATA
synfras-1.0.1.dist-info/WHEEL
synfras-1.0.1.dist-info/RECORD
