Metadata-Version: 2.1
Name: synfras
Version: 1.0.1
Summary: 
Author: Trung Dang
Author-email: dangtrung96@gmail.com
Requires-Python: >=3.11,<4.0
Classifier: Programming Language :: Python :: 3
Classifier: Programming Language :: Python :: 3.11
Classifier: Programming Language :: Python :: 3.12
Requires-Dist: dynaconf (>=3.2.4,<4.0.0)
Requires-Dist: pandas (>=2.2.1,<3.0.0)
Requires-Dist: sqlalchemy (>=2.0.27,<3.0.0)
Requires-Dist: tqdm (>=4.66.2,<5.0.0)
